wracker/__init__.py
wracker/__main__.py
wracker/entrypoints.py
wracker/requirement_parser.py
wracker/util.py
wracker/which.py
wracker/pkg_resources/__init__.py
wracker-0.4.0.dist-info/DESCRIPTION.rst
wracker-0.4.0.dist-info/METADATA
wracker-0.4.0.dist-info/RECORD
wracker-0.4.0.dist-info/WHEEL
wracker-0.4.0.dist-info/entry_points.txt
wracker-0.4.0.dist-info/metadata.json
wracker-0.4.0.dist-info/top_level.txt
