Metadata-Version: 2.0
Name: wracker
Version: 0.4.0
Summary: A Bundler clone for Python
Home-page: https://github.com/dan-passaro/wracker
Author: Dan Passaro
Author-email: danpassaro@gmail.com
License: License :: OSI Approved :: GNU Affero General Public License v3 or later (AGPLv3+)
Platform: Operating System :: POSIX
Classifier: Development Status :: 2 - Pre-Alpha
Classifier: Intended Audience :: Developers
Classifier: Programming Language :: Python
Classifier: Topic :: Software Development :: Build Tools
